{
    "battery1": {
        "datetime": "datetime64[ns]",
        "isoqui": "int64",
        "hwconffau": "int64",
        "msdopen": "int64",
        "daicommerr": "int64",
        "daicommwarn": "int64",
        "hvilexadc": "int64",
        "hvilinerr": "int64",
        "hvilinadc": "int64",
        "isoadc": "int64",
        "bduopwarn": "int64",
        "bduoperr": "int64",
        "inpresvld": "int64",
        "outpresvld": "int64",
        "cellbalerr": "int64",
        "aux5vvld": "int64",
        "enthr": "int64",
        "disenthr": "int64",
        "maxchrpwr": "float64",
        "maxdispwr": "float64",
        "cellvmin": "float64",
        "cellvmax": "float64",
        "coolreq": "int64",
        "heatreq": "int64",
        "isoresneg": "int64",
        "isorespos": "int64",
        "soc": "float64",
        "soh": "int64",
        "enrema": "float64",
        "cellsocmin": "float64",
        "cellsocmax": "float64",
        "tempavg": "int64",
        "tempmax": "int64",
        "tempmin": "int64",
        "inpres": "float64",
        "outpres": "float64",
        "bdutemp": "int64",
        "bduhum": "int64",
        "chrtime": "int64",
        "distime": "int64",
        "fullcharcou": "int64",
        "optime": "int64",
        "remchrtime": "int64",
        "maxchrcurr": "float64",
        "maxdiscurr": "float64",
        "maxchrpwrchrgr": "float64",
        "maxchrcurrchrgr": "float64",
        "linkvol": "float64",
        "packcurr": "float64",
        "packvol": "float64",
        "battsts": "int64",
        "negrly": "int64",
        "posrly": "int64",
        "prerly": "int64",
        "endchrsts": "int64",
        "isoact": "int64",
        "can1": "int64",
        "can3": "int64",
        "led": "int64",
        "packid": "int64",
        "maxpacksta": "int64",
        "can3baud": "int64",
        "heartb": "int64",
        "connpacksta": "int64",
        "accelhi": "int64",
        "cellbal": "int64",
        "msglossconf": "int64",
        "hwver": "int64",
        "swver": "int64",
        "source_file": "object"
    },
    "chargecontroller1": {
        "datetime": "datetime64[ns]",
        "pp": "int64",
        "cp": "int64",
        "accharposs": "int64",
        "cpduty": "int64",
        "inlactemp": "float64",
        "inldctemp": "float64",
        "hvswtemp": "float64",
        "hvplugtemp": "float64",
        "auxtemp": "float64",
        "evseid": "int64",
        "prescurr": "float64",
        "presvolt": "float64",
        "crc": "int64",
        "seqcount": "int64",
        "hvsw1statereq": "int64",
        "hvsw2statereq": "int64",
        "plugstate": "int64",
        "il1state": "int64",
        "il2state": "int64",
        "emergshut": "int64",
        "hwvers": "int64",
        "canvers": "int64",
        "swmajvers": "int64",
        "swbuildvers": "int64",
        "swminvers": "int64",
        "mincurrlim": "float64",
        "minvoltlim": "float64",
        "enertobedeli": "int64",
        "peakcurrripp": "float64",
        "currregtol": "float64",
        "evsestate": "int64",
        "powlimach": "int64",
        "currlimach": "int64",
        "voltlimach": "int64",
        "wakeupreas": "int64",
        "lockstate": "int64",
        "hvswstate": "int64",
        "cclstate": "int64",
        "targcurr": "float64",
        "chargmode": "int64",
        "dtc_awl": "int64",
        "dtc_pl": "int64",
        "dtc_rsl": "int64",
        "actchargprot": "int64",
        "maxcurrlim": "float64",
        "maxvoltlim": "float64",
        "maxpowlim": "int64",
        "errorno": "int64",
        "evsestatcode": "int64",
        "buttonstate": "int64",
        "shutdownreq": "int64",
        "source_file": "object"
    },
    "chiller1": {
        "datetime": "datetime64[ns]",
        "hypstat": "float64",
        "hyptimeout": "float64",
        "dcdcstat": "float64",
        "dcdctimeout": "float64",
        "wpintstat": "float64",
        "wpinttimeout": "float64",
        "wpextstat": "float64",
        "wpexttimeout": "float64",
        "hvhstat": "float64",
        "hvhtimeout": "float64",
        "fan1stat": "float64",
        "fan1timeout": "float64",
        "fan2stat": "float64",
        "fan2timeout": "float64",
        "hvundvolt": "float64",
        "hvovervolt": "float64",
        "lvundvolt": "float64",
        "lvovervolt": "float64",
        "vdd12undvolt": "float64",
        "vdd12overvolt": "float64",
        "coollevstat": "float64",
        "stcsensstat": "float64",
        "ecuerr": "float64",
        "stm": "float64",
        "detconfig": "float64",
        "coolavail": "float64",
        "heatavail": "float64",
        "detcanprot": "float64",
        "fan1speed": "float64",
        "fan2speed": "float64",
        "pumpextspeed": "float64",
        "pumpintspeed": "float64",
        "cooltemp": "float64",
        "powconshvh": "float64",
        "powconshyper": "float64",
        "powlimcalc": "float64",
        "sliinppwr": "float64",
        "hv": "float64",
        "cmpr": "float64",
        "rel": "float64",
        "heatrsts": "float64",
        "hvilsts": "float64",
        "mode": "float64",
        "cooltlvl": "float64",
        "source_file": "object"
    },
    "ccl1": {
        "datetime": "datetime64[ns]",
        "pp": "int64",
        "cp": "int64",
        "accharposs": "int64",
        "cpduty": "int64",
        "inlactemp": "float64",
        "inldctemp": "float64",
        "hvswtemp": "float64",
        "hvplugtemp": "float64",
        "auxtemp": "float64",
        "evseid": "int64",
        "prescurr": "float64",
        "presvolt": "float64",
        "crc": "int64",
        "seqcount": "int64",
        "hvsw1statereq": "int64",
        "hvsw2statereq": "int64",
        "plugstate": "int64",
        "il1state": "int64",
        "il2state": "int64",
        "emergshut": "int64",
        "hwvers": "int64",
        "canvers": "int64",
        "swmajvers": "int64",
        "swbuildvers": "int64",
        "swminvers": "int64",
        "mincurrlim": "float64",
        "minvoltlim": "float64",
        "enertobedeli": "int64",
        "peakcurrripp": "float64",
        "currregtol": "float64",
        "evsestate": "int64",
        "powlimach": "int64",
        "currlimach": "int64",
        "voltlimach": "int64",
        "wakeupreas": "int64",
        "lockstate": "int64",
        "hvswstate": "int64",
        "cclstate": "int64",
        "targcurr": "float64",
        "chargmode": "int64",
        "dtc_awl": "int64",
        "dtc_pl": "int64",
        "dtc_rsl": "int64",
        "actchargprot": "int64",
        "maxcurrlim": "float64",
        "maxvoltlim": "float64",
        "maxpowlim": "int64",
        "errorno": "int64",
        "evsestatcode": "int64",
        "buttonstate": "int64",
        "shutdownreq": "int64",
        "source_file": "object"
    },
    "dcdc": {
        "datetime": "datetime64[ns]",
        "currout": "int64",
        "voltout": "int64",
        "temp": "int64",
        "enabled": "int64",
        "voltsetpoint": "int64",
        "inputcurr": "int64",
        "inputvolt": "int64",
        "source_file": "object"
    },
    "drive1": {
        "datetime": "datetime64[ns]",
        "modatemp": "float64",
        "modbtemp": "float64",
        "modctemp": "float64",
        "gatedritemp": "float64",
        "conttemp": "float64",
        "rtd1temp": "float64",
        "rtd2temp": "float64",
        "stallburtemp": "float64",
        "cooltemp": "float64",
        "hotspottemp": "float64",
        "mottemp": "float64",
        "torqshud": "float64",
        "oiltemp": "float64",
        "oilpres": "float64",
        "anin4": "float64",
        "anin5": "float64",
        "anin6": "float64",
        "diin1": "int64",
        "diin2": "int64",
        "diin3": "int64",
        "diin4": "int64",
        "diin5": "int64",
        "diin6": "int64",
        "diin7": "int64",
        "diin8": "int64",
        "motangelec": "float64",
        "motrpm": "int64",
        "elecoutfreq": "float64",
        "phaatemp": "float64",
        "phabtemp": "float64",
        "phactemp": "float64",
        "dccurr": "float64",
        "dcvolt": "float64",
        "outvolt": "float64",
        "vabvd": "float64",
        "vbcvq": "float64",
        "vdff": "float64",
        "vqff": "float64",
        "id": "float64",
        "iq": "float64",
        "ref15": "float64",
        "ref25": "float64",
        "ref50": "float64",
        "ref120": "float64",
        "vsm": "int64",
        "pwm": "int64",
        "invsta": "int64",
        "r1": "int64",
        "r2": "int64",
        "r3": "int64",
        "r4": "int64",
        "r5": "int64",
        "r6": "int64",
        "run": "int64",
        "selfsens": "int64",
        "dissta": "int64",
        "commmode": "int64",
        "rollcoun": "int64",
        "enasta": "int64",
        "burstmod": "int64",
        "keysta": "int64",
        "enalock": "int64",
        "dircomm": "int64",
        "bmsact": "int64",
        "bmstlim": "int64",
        "limmaxrpm": "int64",
        "limhotspot": "int64",
        "lowrpmlim": "int64",
        "limcoolder": "int64",
        "limstallbur": "int64",
        "postlo": "int64",
        "posthi": "int64",
        "runlo": "int64",
        "runhi": "int64",
        "commtorq": "float64",
        "torqfeed": "float64",
        "powontime": "float64",
        "modind": "float64",
        "fluxweakout": "float64",
        "idcomm": "float64",
        "iqcomm": "float64",
        "projcode": "int64",
        "swver": "int64",
        "mmdd": "int64",
        "yyyy": "int64",
        "diagrec": "int64",
        "diagseg": "int64",
        "diaggres": "float64",
        "diaggobs": "float64",
        "diagsin": "int64",
        "ftorqcomm": "float64",
        "ftorqfeed": "float64",
        "fmotrpm": "int64",
        "fdcvolt": "float64",
        "parrespadd": "int64",
        "parrespwri": "int64",
        "parrespdat": "int64",
        "source_file": "object"
    },
    "drive2": {
        "datetime": "datetime64[ns]",
        "modatemp": "float64",
        "modbtemp": "float64",
        "modctemp": "float64",
        "gatedritemp": "float64",
        "conttemp": "float64",
        "rtd1temp": "float64",
        "rtd2temp": "float64",
        "stallburtemp": "float64",
        "cooltemp": "float64",
        "hotspottemp": "float64",
        "mottemp": "float64",
        "torqshud": "float64",
        "oiltemp": "float64",
        "oilpres": "float64",
        "anin4": "float64",
        "anin5": "float64",
        "anin6": "float64",
        "diin1": "float64",
        "diin2": "float64",
        "diin3": "float64",
        "diin4": "float64",
        "diin5": "float64",
        "diin6": "float64",
        "diin7": "float64",
        "diin8": "float64",
        "motangelec": "float64",
        "motrpm": "float64",
        "elecoutfreq": "float64",
        "phaatemp": "float64",
        "phabtemp": "float64",
        "phactemp": "float64",
        "dccurr": "float64",
        "dcvolt": "float64",
        "outvolt": "float64",
        "vabvd": "float64",
        "vbcvq": "float64",
        "vdff": "float64",
        "vqff": "float64",
        "id": "float64",
        "iq": "float64",
        "ref15": "float64",
        "ref25": "float64",
        "ref50": "float64",
        "ref120": "float64",
        "vsm": "float64",
        "pwm": "float64",
        "invsta": "float64",
        "r1": "float64",
        "r2": "float64",
        "r3": "float64",
        "r4": "float64",
        "r5": "float64",
        "r6": "float64",
        "run": "float64",
        "selfsens": "float64",
        "dissta": "float64",
        "commmode": "float64",
        "rollcoun": "float64",
        "enasta": "float64",
        "burstmod": "float64",
        "keysta": "float64",
        "enalock": "float64",
        "dircomm": "float64",
        "bmsact": "float64",
        "bmstlim": "float64",
        "limmaxrpm": "float64",
        "limhotspot": "float64",
        "lowrpmlim": "float64",
        "limcoolder": "float64",
        "limstallbur": "float64",
        "postlo": "float64",
        "posthi": "float64",
        "runlo": "float64",
        "runhi": "float64",
        "commtorq": "float64",
        "torqfeed": "float64",
        "powontime": "float64",
        "modind": "float64",
        "fluxweakout": "float64",
        "idcomm": "float64",
        "iqcomm": "float64",
        "projcode": "float64",
        "swver": "float64",
        "mmdd": "float64",
        "yyyy": "float64",
        "diagrec": "float64",
        "diagseg": "float64",
        "diaggres": "float64",
        "diaggobs": "float64",
        "diagsin": "float64",
        "ftorqcomm": "float64",
        "ftorqfeed": "float64",
        "fmotrpm": "float64",
        "fdcvolt": "float64",
        "parrespadd": "float64",
        "parrespwri": "float64",
        "parrespdat": "float64",
        "source_file": "object"
    },
    "vehicle": {
        "datetime": "datetime64[ns]",
        "plc_hb": "int64",
        "24volt": "int64",
        "vcumode": "int64",
        "vehstate": "int64",
        "whlspd": "int64",
        "uptime": "object",
        "downtime": "object",
        "gearchngetime": "object",
        "bodypos": "int64",
        "throttle": "float64",
        "bodyup": "int64",
        "brakeairpres": "int64",
        "brakeoiltemp": "int64",
        "downshifton": "int64",
        "hoistposave": "int64",
        "keyaccessvolt": "int64",
        "ignition": "int64",
        "parkbrakeleft": "int64",
        "parkbrakeright": "int64",
        "retarder": "float64",
        "flstrut": "int64",
        "frstrut": "int64",
        "rlstrut": "int64",
        "rrstrut": "int64",
        "gearreq": "int64",
        "gearact": "int64",
        "upshifton": "int64",
        "wspeedleft": "int64",
        "wspeedright": "int64",
        "pdpposconclos": "int64",
        "pdpnegconclos": "int64",
        "pdpchilconclos": "int64",
        "pdpdrive1contclos": "int64",
        "pdpdrive2contclos": "int64",
        "pdpaux1contclos": "int64",
        "chillconn": "int64",
        "driveconn": "int64",
        "auxconn": "int64",
        "pdpposconn": "int64",
        "pdpnegconn": "int64",
        "pdpdriveconn": "int64",
        "pdpauxconn": "int64",
        "pdpchillconn": "int64",
        "pdpdcdcconn": "int64",
        "pressval": "float64",
        "tempval": "float64",
        "lvvolt": "int64",
        "procestemp": "int64",
        "pcbtemp": "int64",
        "vibval": "float64",
        "g1outvolt": "int64",
        "g2outvolt": "int64",
        "g3goutvolt": "int64",
        "transdrainon": "int64",
        "batton": "int64",
        "dcdcon": "int64",
        "driveon": "int64",
        "auxon": "int64",
        "incli_x_raw": "int64",
        "incli_y_raw": "int64",
        "incli_x": "float64",
        "incli_y": "float64",
        "can0errtx": "int64",
        "can0errrx": "int64",
        "can0busload": "int64",
        "can0busstate": "int64",
        "can0messcount": "int64",
        "can1errtx": "int64",
        "can1errrx": "int64",
        "can1busload": "int64",
        "can1busstate": "int64",
        "can1messcount": "int64",
        "can2errtx": "int64",
        "can2errrx": "int64",
        "can2busload": "int64",
        "can2busstate": "int64",
        "can2messcount": "int64",
        "can3errtx": "int64",
        "can3errrx": "int64",
        "can3busload": "int64",
        "can3busstate": "int64",
        "can3messcount": "int64",
        "rpmbefore": "int64",
        "rpmafter": "int64",
        "gearchanged": "int64",
        "rpminit": "int64",
        "source_file": "object",
        "shutdownsafe": "float64",
        "fault": "object"
    },
    "auxiliary": {
        "datetime": "datetime64[ns]",
        "cansigacttorq": "float64",
        "dcbuscurr": "float64",
        "diin1": "float64",
        "diin2": "float64",
        "diin3": "float64",
        "diin4": "float64",
        "diin5": "float64",
        "diin6": "float64",
        "diin7": "float64",
        "diin8": "float64",
        "diin9": "float64",
        "encin2a": "float64",
        "encin2b": "float64",
        "diin13": "float64",
        "encin1c": "float64",
        "encin1a": "float64",
        "encin1b": "float64",
        "abiacccurr": "float64",
        "idarms": "float64",
        "iqarms": "float64",
        "udref": "float64",
        "uqref": "float64",
        "actlimtype": "float64",
        "regstat": "float64",
        "sensang": "float64",
        "iq": "float64",
        "id": "float64",
        "reatoswon": "float64",
        "swon": "float64",
        "ena": "float64",
        "trip": "float64",
        "currabired": "float64",
        "currboosact": "float64",
        "erract": "float64",
        "warnact": "float64",
        "regen": "float64",
        "odout1on": "float64",
        "odout2on": "float64",
        "odout3on": "float64",
        "odout4on": "float64",
        "odout5on": "float64",
        "odout6on": "float64",
        "cansigrotspeedinrpm": "float64",
        "cansigrmsmotcurr": "float64",
        "filtvolt": "float64",
        "event1": "float64",
        "event2": "float64",
        "event3": "float64",
        "event4": "float64",
        "mottemp": "float64",
        "heatstemp": "float64",
        "actcontmode": "float64",
        "actevent": "float64",
        "dcbuspow": "float64",
        "upeaknorm": "float64",
        "voltang": "float64",
        "reftorq": "float64",
        "source_file": "object"
    }
}